<?xml version="1.0" standalone="yes"?>
<?xml-stylesheet href="x2script.xsl" type="text/xsl"?>
<!-- Generated using X-Studio -->
<script>
	<name>!ship.cmd.boardship.preload</name>
	<version>3</version>
	<engineversion>50</engineversion>
	<description>Ship Preload COMMAND ATTACK BOARDSHIP</description>
	<arguments>
		<argument index="1" name="target" type="Var/Ship" desc="" />
	</arguments>
	<sourcetext>
		<line linenr="001" indent="">
			<var>$marines</var>
			<text> </text>
			<text>=</text>
			<text> </text>
			<var>[THIS]</var>
			<text>-&gt;</text>
			<text> </text>
			<text>get</text>
			<text> </text>
			<text>marines</text>
			<text> </text>
			<text>array</text>
		</line>
		<line linenr="002" indent="">
			<var>$marines</var>
			<text> </text>
			<text>=</text>
			<text> </text>
			<text>size</text>
			<text> </text>
			<text>of</text>
			<text> </text>
			<text>array</text>
			<text> </text>
			<var>$marines</var>
		</line>
		<line linenr="003" indent="">
			<text>if</text>
			<text> </text>
			<var>$marines</var>
			<text> </text>
			<text>==</text>
			<text> </text>
			<var>0</var>
		</line>
		<line linenr="004" indent="&#160;">
			<var>$t</var>
			<text> </text>
			<text>=</text>
			<text> </text>
			<text>sprintf</text>
			<text>:</text>
			<text> </text>
			<text>pageid</text>
			<text>=</text>
			<var>8396</var>
			<text> </text>
			<text>textid</text>
			<text>=</text>
			<var>101</var>
			<text>,</text>
			<text> </text>
			<text>'No marines onboard'</text>
			<text>,</text>
			<text> </text>
			<var>null</var>
			<text>,</text>
			<text> </text>
			<var>null</var>
			<text>,</text>
			<text> </text>
			<var>null</var>
			<text>,</text>
			<text> </text>
			<var>null</var>
		</line>
		<line linenr="005" indent="&#160;">
			<text>display</text>
			<text> </text>
			<text>info</text>
			<text> </text>
			<text>box</text>
			<text>:</text>
			<text> </text>
			<text>text</text>
			<text>=</text>
			<text> </text>
			<var>$t</var>
			<text>,</text>
			<text> </text>
			<text>icon</text>
			<text>=</text>
			<text> </text>
			<var>66</var>
			<text>,</text>
			<text> </text>
			<text>timeout</text>
			<text>=</text>
			<text> </text>
			<var>5000</var>
			<text>,</text>
			<text> </text>
			<text>fadeout</text>
			<text>=</text>
			<text> </text>
			<var>1000</var>
		</line>
		<line linenr="006" indent="&#160;">
			<text>return</text>
			<text> </text>
			<var>null</var>
		</line>
		<line linenr="007" indent="">
			<text>end</text>
		</line>
		<line linenr="008" indent="" />
		<line linenr="009" indent="">
			<text>if</text>
			<text> </text>
			<var>[THIS]</var>
			<text>-&gt;</text>
			<text> </text>
			<text>is</text>
			<text> </text>
			<text>docked</text>
		</line>
		<line linenr="010" indent="&#160;">
			<var>$t</var>
			<text> </text>
			<text>=</text>
			<text> </text>
			<text>sprintf</text>
			<text>:</text>
			<text> </text>
			<text>pageid</text>
			<text>=</text>
			<var>8396</var>
			<text> </text>
			<text>textid</text>
			<text>=</text>
			<var>101</var>
			<text>,</text>
			<text> </text>
			<text>'Cannot launch marines while docked'</text>
			<text>,</text>
			<text> </text>
			<var>null</var>
			<text>,</text>
			<text> </text>
			<var>null</var>
			<text>,</text>
			<text> </text>
			<var>null</var>
			<text>,</text>
			<text> </text>
			<var>null</var>
		</line>
		<line linenr="011" indent="&#160;">
			<text>display</text>
			<text> </text>
			<text>info</text>
			<text> </text>
			<text>box</text>
			<text>:</text>
			<text> </text>
			<text>text</text>
			<text>=</text>
			<text> </text>
			<var>$t</var>
			<text>,</text>
			<text> </text>
			<text>icon</text>
			<text>=</text>
			<text> </text>
			<var>66</var>
			<text>,</text>
			<text> </text>
			<text>timeout</text>
			<text>=</text>
			<text> </text>
			<var>5000</var>
			<text>,</text>
			<text> </text>
			<text>fadeout</text>
			<text>=</text>
			<text> </text>
			<var>1000</var>
		</line>
		<line linenr="012" indent="&#160;">
			<text>return</text>
			<text> </text>
			<var>null</var>
		</line>
		<line linenr="013" indent="">
			<text>end</text>
		</line>
		<line linenr="014" indent="" />
		<line linenr="015" indent="">
			<var>$hasTransporter</var>
			<text> </text>
			<text>=</text>
			<text> </text>
			<var>[THIS]</var>
			<text>-&gt;</text>
			<text> </text>
			<text>get</text>
			<text> </text>
			<text>amount</text>
			<text> </text>
			<text>of</text>
			<text> </text>
			<text>ware</text>
			<text> </text>
			<var>{Transporter Device}</var>
			<text> </text>
			<text>in</text>
			<text> </text>
			<text>cargo</text>
			<text> </text>
			<text>bay</text>
		</line>
		<line linenr="016" indent="">
			<text>if</text>
			<text> </text>
			<text>!</text>
			<var>$hasTransporter</var>
		</line>
		<line linenr="017" indent="&#160;">
			<var>$t</var>
			<text> </text>
			<text>=</text>
			<text> </text>
			<text>sprintf</text>
			<text>:</text>
			<text> </text>
			<text>pageid</text>
			<text>=</text>
			<var>8396</var>
			<text> </text>
			<text>textid</text>
			<text>=</text>
			<var>101</var>
			<text>,</text>
			<text> </text>
			<text>'A Transporter Device is needed to initiate a boarding operation'</text>
			<text>,</text>
			<text> </text>
			<var>null</var>
			<text>,</text>
			<text> </text>
			<var>null</var>
			<text>,</text>
			<text> </text>
			<var>null</var>
			<text>,</text>
			<text> </text>
			<var>null</var>
		</line>
		<line linenr="018" indent="&#160;">
			<text>display</text>
			<text> </text>
			<text>info</text>
			<text> </text>
			<text>box</text>
			<text>:</text>
			<text> </text>
			<text>text</text>
			<text>=</text>
			<text> </text>
			<var>$t</var>
			<text>,</text>
			<text> </text>
			<text>icon</text>
			<text>=</text>
			<text> </text>
			<var>66</var>
			<text>,</text>
			<text> </text>
			<text>timeout</text>
			<text>=</text>
			<text> </text>
			<var>5000</var>
			<text>,</text>
			<text> </text>
			<text>fadeout</text>
			<text>=</text>
			<text> </text>
			<var>1000</var>
		</line>
		<line linenr="019" indent="&#160;">
			<text>return</text>
			<text> </text>
			<var>null</var>
		</line>
		<line linenr="020" indent="">
			<text>end</text>
		</line>
		<line linenr="021" indent="" />
		<line linenr="022" indent="">
			<text>do</text>
			<text> </text>
			<text>if</text>
			<text> </text>
			<var>$target</var>
			<text> </text>
			<text>==</text>
			<text> </text>
			<var>[PLAYERSHIP]</var>
			<text> </text>
			<text>OR</text>
			<text> </text>
			<var>[THIS]</var>
			<text> </text>
			<text>!=</text>
			<text> </text>
			<var>[PLAYERSHIP]</var>
		</line>
		<line linenr="023" indent="&#160;">
			<var>$target</var>
			<text> </text>
			<text>=</text>
			<text> </text>
			<var>[THIS]</var>
			<text>-&gt;</text>
			<text> </text>
			<text>get</text>
			<text> </text>
			<text>user</text>
			<text> </text>
			<text>input</text>
			<text> </text>
			<text>without</text>
			<text> </text>
			<text>sector</text>
			<text>:</text>
			<text> </text>
			<text>type</text>
			<text>=</text>
			<var>[Var/Ship]</var>
			<text>,</text>
			<text> </text>
			<text>title</text>
			<text>=</text>
			<text>'Select a ship to board'</text>
		</line>
		<line linenr="024" indent="" />
		<line linenr="025" indent="">
			<var>$target.isBoardable</var>
			<text> </text>
			<text>=</text>
			<text> </text>
			<var>$target</var>
			<text>-&gt;</text>
			<text> </text>
			<text>is</text>
			<text> </text>
			<text>ship</text>
			<text> </text>
			<text>boardable</text>
		</line>
		<line linenr="026" indent="">
			<var>$target.isBoardingDisabled</var>
			<text> </text>
			<text>=</text>
			<text> </text>
			<var>$target</var>
			<text>-&gt;</text>
			<text> </text>
			<text>is</text>
			<text> </text>
			<text>boarding</text>
			<text> </text>
			<text>disabled</text>
		</line>
		<line linenr="027" indent="">
			<var>$target.class</var>
			<text> </text>
			<text>=</text>
			<text> </text>
			<var>$target</var>
			<text>-&gt;</text>
			<text> </text>
			<text>get</text>
			<text> </text>
			<text>object</text>
			<text> </text>
			<text>class</text>
		</line>
		<line linenr="028" indent="">
			<var>$target.owner</var>
			<text> </text>
			<text>=</text>
			<text> </text>
			<var>$target</var>
			<text>-&gt;</text>
			<text> </text>
			<text>get</text>
			<text> </text>
			<text>owner</text>
			<text> </text>
			<text>race</text>
		</line>
		<line linenr="029" indent="">
			<var>$relation</var>
			<text> </text>
			<text>=</text>
			<text> </text>
			<var>$target</var>
			<text>-&gt;</text>
			<text> </text>
			<text>get</text>
			<text> </text>
			<text>relation</text>
			<text> </text>
			<text>to</text>
			<text> </text>
			<text>race</text>
			<text> </text>
			<var>[Player]</var>
		</line>
		<line linenr="030" indent="">
			<var>$distance</var>
			<text> </text>
			<text>=</text>
			<text> </text>
			<text>get</text>
			<text> </text>
			<text>distance</text>
			<text> </text>
			<text>between</text>
			<text> </text>
			<var>[THIS]</var>
			<text> </text>
			<text>and</text>
			<text> </text>
			<var>$target</var>
		</line>
		<line linenr="031" indent="">
			<var>$shield</var>
			<text> </text>
			<text>=</text>
			<text> </text>
			<var>$target</var>
			<text>-&gt;</text>
			<text> </text>
			<text>get</text>
			<text> </text>
			<text>shield</text>
			<text> </text>
			<text>percent</text>
		</line>
		<line linenr="032" indent="" />
		<line linenr="033" indent="" interruptable="@">
			<text>if</text>
			<text> </text>
			<var>[NULL]</var>
			<text> </text>
			<text>-&gt;</text>
			<text> </text>
			<text>call</text>
			<text> </text>
			<text>script</text>
			<text> </text>
			<call>Mayhem.IsImprovementUnlocked</call>
			<text>:</text>
			<text> </text>
			<text>improvement</text>
			<text>=</text>
			<text>'Shield expertise'</text>
		</line>
		<line linenr="034" indent="&#160;">
			<var>$requiredShield</var>
			<text> </text>
			<text>=</text>
			<text> </text>
			<var>50</var>
		</line>
		<line linenr="035" indent="">
			<text>else</text>
		</line>
		<line linenr="036" indent="&#160;">
			<var>$requiredShield</var>
			<text> </text>
			<text>=</text>
			<text> </text>
			<var>10</var>
		</line>
		<line linenr="037" indent="">
			<text>end</text>
		</line>
		<line linenr="038" indent="">
			<var>$requiredDistance</var>
			<text> </text>
			<text>=</text>
			<text> </text>
			<text>get</text>
			<text> </text>
			<text>transporter</text>
			<text> </text>
			<text>range</text>
		</line>
		<line linenr="039" indent="" />
		<line linenr="040" indent="">
			<text>if</text>
			<text> </text>
			<var>$target</var>
			<text>-&gt;</text>
			<text> </text>
			<text>exists</text>
		</line>
		<line linenr="041" indent="&#160;">
			<var>$expedition</var>
			<text> </text>
			<text>=</text>
			<text> </text>
			<var>$target</var>
			<text>-&gt;</text>
			<text> </text>
			<text>get</text>
			<text> </text>
			<text>local</text>
			<text> </text>
			<text>variable</text>
			<text>:</text>
			<text> </text>
			<text>name</text>
			<text>=</text>
			<text>'mayhem_expedition'</text>
		</line>
		<line linenr="042" indent="&#160;">
			<text>if</text>
			<text> </text>
			<text>not</text>
			<text> </text>
			<text>table</text>
			<text> </text>
			<text>get</text>
			<text> </text>
			<var>$expedition</var>
			<text> </text>
			<text>(</text>
			<text> </text>
			<text>'inProgress'</text>
			<text> </text>
			<text>)</text>
		</line>
		<line linenr="043" indent="&#160;&#160;">
			<text>if</text>
			<text> </text>
			<var>$target.isBoardable</var>
			<text> </text>
			<text>AND</text>
			<text> </text>
			<text>!</text>
			<var>$target.isBoardingDisabled</var>
		</line>
		<line linenr="044" indent="&#160;&#160;&#160;">
			<text>if</text>
			<text> </text>
			<var>$relation</var>
			<text> </text>
			<text>==</text>
			<text> </text>
			<var>[Foe]</var>
		</line>
		<line linenr="045" indent="&#160;&#160;&#160;&#160;">
			<text>if</text>
			<text> </text>
			<var>$distance</var>
			<text> </text>
			<text>&lt;=</text>
			<text> </text>
			<var>$requiredDistance</var>
		</line>
		<line linenr="046" indent="&#160;&#160;&#160;&#160;&#160;">
			<text>if</text>
			<text> </text>
			<var>$shield</var>
			<text> </text>
			<text>&lt;</text>
			<text> </text>
			<var>$requiredShield</var>
		</line>
		<line linenr="047" indent="&#160;&#160;&#160;&#160;&#160;&#160;">
			<var>$squad</var>
			<text> </text>
			<text>=</text>
			<text> </text>
			<text>array</text>
			<text> </text>
			<text>alloc</text>
			<text>:</text>
			<text> </text>
			<text>size</text>
			<text>=</text>
			<var>0</var>
		</line>
		<line linenr="048" indent="&#160;&#160;&#160;&#160;&#160;&#160;">
			<var>$marines</var>
			<text> </text>
			<text>=</text>
			<text> </text>
			<text>get</text>
			<text> </text>
			<text>global</text>
			<text> </text>
			<text>variable</text>
			<text>:</text>
			<text> </text>
			<text>name</text>
			<text>=</text>
			<text>'mayhem_marines'</text>
		</line>
		<line linenr="049" indent="&#160;&#160;&#160;&#160;&#160;&#160;">
			<var>$equipment</var>
			<text> </text>
			<text>=</text>
			<text> </text>
			<text>get</text>
			<text> </text>
			<text>global</text>
			<text> </text>
			<text>variable</text>
			<text>:</text>
			<text> </text>
			<text>name</text>
			<text>=</text>
			<text>'mayhem_equipment'</text>
		</line>
		<line linenr="050" indent="&#160;&#160;&#160;&#160;&#160;&#160;">
			<var>$thisName</var>
			<text> </text>
			<text>=</text>
			<text> </text>
			<var>[THIS]</var>
			<text>-&gt;</text>
			<text> </text>
			<text>get</text>
			<text> </text>
			<text>name</text>
		</line>
		<line linenr="051" indent="&#160;&#160;&#160;&#160;&#160;&#160;" interruptable="@">
			<var>$squadSize</var>
			<text> </text>
			<text>=</text>
			<text> </text>
			<var>[NULL]</var>
			<text>-&gt;</text>
			<text> </text>
			<text>call</text>
			<text> </text>
			<text>script</text>
			<text> </text>
			<call>Mayhem.GetShipSquadSize</call>
			<text> </text>
			<text>:</text>
			<text> </text>
			<text>class</text>
			<text>=</text>
			<var>$target.class</var>
		</line>
		<line linenr="052" indent="&#160;&#160;&#160;&#160;&#160;&#160;" />
		<line linenr="053" indent="&#160;&#160;&#160;&#160;&#160;&#160;" interruptable="@">
			<var>$squadNames</var>
			<text> </text>
			<text>=</text>
			<text> </text>
			<var>[NULL]</var>
			<text>-&gt;</text>
			<text> </text>
			<text>call</text>
			<text> </text>
			<text>script</text>
			<text> </text>
			<call>Menu.BoardingPreload</call>
			<text> </text>
			<text>:</text>
			<text> </text>
			<text>this</text>
			<text>=</text>
			<var>[THIS]</var>
			<text> </text>
			<text>target</text>
			<text>=</text>
			<var>$target</var>
			<text> </text>
			<text>squadSize</text>
			<text>=</text>
			<var>$squadSize</var>
		</line>
		<line linenr="054" indent="&#160;&#160;&#160;&#160;&#160;&#160;" />
		<line linenr="055" indent="&#160;&#160;&#160;&#160;&#160;&#160;">
			<comment>* ---------------------------------------------------------------------------------------------------------------------------------</comment>
		</line>
		<line linenr="056" indent="&#160;&#160;&#160;&#160;&#160;&#160;" />
		<line linenr="057" indent="&#160;&#160;&#160;&#160;&#160;&#160;">
			<text>if</text>
			<text> </text>
			<text>is</text>
			<text> </text>
			<text>datatype</text>
			<text>[</text>
			<var>$squadNames</var>
			<text>]</text>
			<text> </text>
			<text>==</text>
			<text> </text>
			<var>[DATATYPE_ARRAY]</var>
		</line>
		<line linenr="058" indent="&#160;&#160;&#160;&#160;&#160;&#160;&#160;">
			<var>$teleportation</var>
			<text> </text>
			<text>=</text>
			<text> </text>
			<var>3</var>
		</line>
		<line linenr="059" indent="&#160;&#160;&#160;&#160;&#160;&#160;&#160;">
			<text>while</text>
			<text> </text>
			<var>$teleportation</var>
		</line>
		<line linenr="060" indent="&#160;&#160;&#160;&#160;&#160;&#160;&#160;&#160;">
			<var>$targetSector</var>
			<text> </text>
			<text>=</text>
			<text> </text>
			<var>$target</var>
			<text>-&gt;</text>
			<text> </text>
			<text>get</text>
			<text> </text>
			<text>sector</text>
		</line>
		<line linenr="061" indent="&#160;&#160;&#160;&#160;&#160;&#160;&#160;&#160;">
			<text>if</text>
			<text> </text>
			<var>$targetSector</var>
			<text> </text>
			<text>!=</text>
			<text> </text>
			<var>[SECTOR]</var>
		</line>
		<line linenr="062" indent="&#160;&#160;&#160;&#160;&#160;&#160;&#160;&#160;&#160;">
			<text>display</text>
			<text> </text>
			<text>info</text>
			<text> </text>
			<text>box</text>
			<text>:</text>
			<text> </text>
			<text>text</text>
			<text>=</text>
			<text> </text>
			<text>'Boarding operation aborted'</text>
			<text>,</text>
			<text> </text>
			<text>icon</text>
			<text>=</text>
			<text> </text>
			<var>0</var>
			<text>,</text>
			<text> </text>
			<text>timeout</text>
			<text>=</text>
			<text> </text>
			<var>5000</var>
			<text>,</text>
			<text> </text>
			<text>fadeout</text>
			<text>=</text>
			<text> </text>
			<var>1000</var>
		</line>
		<line linenr="063" indent="&#160;&#160;&#160;&#160;&#160;&#160;&#160;&#160;&#160;">
			<text>return</text>
			<text> </text>
			<var>null</var>
		</line>
		<line linenr="064" indent="&#160;&#160;&#160;&#160;&#160;&#160;&#160;&#160;">
			<text>end</text>
		</line>
		<line linenr="065" indent="&#160;&#160;&#160;&#160;&#160;&#160;&#160;&#160;">
			<text>if</text>
			<text> </text>
			<var>$teleportation</var>
			<text> </text>
			<text>==</text>
			<text> </text>
			<var>1</var>
		</line>
		<line linenr="066" indent="&#160;&#160;&#160;&#160;&#160;&#160;&#160;&#160;&#160;">
			<var>$t</var>
			<text> </text>
			<text>=</text>
			<text> </text>
			<text>'Launching team in '</text>
			<text> </text>
			<text>+</text>
			<text> </text>
			<var>$teleportation</var>
			<text> </text>
			<text>+</text>
			<text> </text>
			<text>' second'</text>
		</line>
		<line linenr="067" indent="&#160;&#160;&#160;&#160;&#160;&#160;&#160;&#160;">
			<text>else</text>
		</line>
		<line linenr="068" indent="&#160;&#160;&#160;&#160;&#160;&#160;&#160;&#160;&#160;">
			<var>$t</var>
			<text> </text>
			<text>=</text>
			<text> </text>
			<text>'Launching team in '</text>
			<text> </text>
			<text>+</text>
			<text> </text>
			<var>$teleportation</var>
			<text> </text>
			<text>+</text>
			<text> </text>
			<text>' seconds'</text>
		</line>
		<line linenr="069" indent="&#160;&#160;&#160;&#160;&#160;&#160;&#160;&#160;">
			<text>end</text>
		</line>
		<line linenr="070" indent="&#160;&#160;&#160;&#160;&#160;&#160;&#160;&#160;">
			<text>display</text>
			<text> </text>
			<text>info</text>
			<text> </text>
			<text>box</text>
			<text>:</text>
			<text> </text>
			<text>text</text>
			<text>=</text>
			<text> </text>
			<var>$t</var>
			<text>,</text>
			<text> </text>
			<text>icon</text>
			<text>=</text>
			<text> </text>
			<var>0</var>
			<text>,</text>
			<text> </text>
			<text>timeout</text>
			<text>=</text>
			<text> </text>
			<var>1500</var>
			<text>,</text>
			<text> </text>
			<text>fadeout</text>
			<text>=</text>
			<text> </text>
			<var>1000</var>
		</line>
		<line linenr="071" indent="&#160;&#160;&#160;&#160;&#160;&#160;&#160;&#160;">
			<text>dec</text>
			<text> </text>
			<var>$teleportation</var>
		</line>
		<line linenr="072" indent="&#160;&#160;&#160;&#160;&#160;&#160;&#160;&#160;" interruptable="@">
			<text>=</text>
			<text> </text>
			<text>wait</text>
			<text> </text>
			<var>1000</var>
			<text> </text>
			<text>ms</text>
		</line>
		<line linenr="073" indent="&#160;&#160;&#160;&#160;&#160;&#160;&#160;">
			<text>end</text>
		</line>
		<line linenr="074" indent="&#160;&#160;&#160;&#160;&#160;&#160;&#160;" />
		<line linenr="075" indent="&#160;&#160;&#160;&#160;&#160;&#160;&#160;">
			<var>$shield</var>
			<text> </text>
			<text>=</text>
			<text> </text>
			<var>$target</var>
			<text>-&gt;</text>
			<text> </text>
			<text>get</text>
			<text> </text>
			<text>shield</text>
			<text> </text>
			<text>percent</text>
		</line>
		<line linenr="076" indent="&#160;&#160;&#160;&#160;&#160;&#160;&#160;">
			<var>$distance</var>
			<text> </text>
			<text>=</text>
			<text> </text>
			<text>get</text>
			<text> </text>
			<text>distance</text>
			<text> </text>
			<text>between</text>
			<text> </text>
			<var>$target</var>
			<text> </text>
			<text>and</text>
			<text> </text>
			<var>[THIS]</var>
		</line>
		<line linenr="077" indent="&#160;&#160;&#160;&#160;&#160;&#160;&#160;">
			<var>$exists</var>
			<text> </text>
			<text>=</text>
			<text> </text>
			<var>$target</var>
			<text>-&gt;</text>
			<text> </text>
			<text>exists</text>
		</line>
		<line linenr="078" indent="&#160;&#160;&#160;&#160;&#160;&#160;&#160;">
			<var>$expedition</var>
			<text> </text>
			<text>=</text>
			<text> </text>
			<var>$target</var>
			<text>-&gt;</text>
			<text> </text>
			<text>get</text>
			<text> </text>
			<text>local</text>
			<text> </text>
			<text>variable</text>
			<text>:</text>
			<text> </text>
			<text>name</text>
			<text>=</text>
			<text>'mayhem_expedition'</text>
		</line>
		<line linenr="079" indent="&#160;&#160;&#160;&#160;&#160;&#160;&#160;">
			<text>if</text>
			<text> </text>
			<text>table</text>
			<text> </text>
			<text>get</text>
			<text> </text>
			<var>$expedition</var>
			<text> </text>
			<text>(</text>
			<text> </text>
			<text>'inProgress'</text>
			<text> </text>
			<text>)</text>
		</line>
		<line linenr="080" indent="&#160;&#160;&#160;&#160;&#160;&#160;&#160;&#160;">
			<var>$t</var>
			<text> </text>
			<text>=</text>
			<text> </text>
			<text>sprintf</text>
			<text>:</text>
			<text> </text>
			<text>pageid</text>
			<text>=</text>
			<var>8396</var>
			<text> </text>
			<text>textid</text>
			<text>=</text>
			<var>101</var>
			<text>,</text>
			<text> </text>
			<text>'A boarding operation is already in progress on this ship'</text>
			<text>,</text>
			<text> </text>
			<var>null</var>
			<text>,</text>
			<text> </text>
			<var>null</var>
			<text>,</text>
			<text> </text>
			<var>null</var>
			<text>,</text>
			<text> </text>
			<var>null</var>
		</line>
		<line linenr="081" indent="&#160;&#160;&#160;&#160;&#160;&#160;&#160;&#160;">
			<text>display</text>
			<text> </text>
			<text>info</text>
			<text> </text>
			<text>box</text>
			<text>:</text>
			<text> </text>
			<text>text</text>
			<text>=</text>
			<text> </text>
			<var>$t</var>
			<text>,</text>
			<text> </text>
			<text>icon</text>
			<text>=</text>
			<text> </text>
			<var>66</var>
			<text>,</text>
			<text> </text>
			<text>timeout</text>
			<text>=</text>
			<text> </text>
			<var>5000</var>
			<text>,</text>
			<text> </text>
			<text>fadeout</text>
			<text>=</text>
			<text> </text>
			<var>1000</var>
		</line>
		<line linenr="082" indent="&#160;&#160;&#160;&#160;&#160;&#160;&#160;&#160;">
			<text>return</text>
			<text> </text>
			<var>null</var>
		</line>
		<line linenr="083" indent="&#160;&#160;&#160;&#160;&#160;&#160;&#160;">
			<text>else</text>
			<text> </text>
			<text>if</text>
			<text> </text>
			<var>$shield</var>
			<text> </text>
			<text>&gt;=</text>
			<text> </text>
			<var>$requiredShield</var>
		</line>
		<line linenr="084" indent="&#160;&#160;&#160;&#160;&#160;&#160;&#160;&#160;">
			<var>$t</var>
			<text> </text>
			<text>=</text>
			<text> </text>
			<text>'The target shield must be lower than '</text>
			<text> </text>
			<text>+</text>
			<text> </text>
			<var>$requiredShield</var>
			<text> </text>
			<text>+</text>
			<text> </text>
			<text>'%'</text>
		</line>
		<line linenr="085" indent="&#160;&#160;&#160;&#160;&#160;&#160;&#160;&#160;">
			<var>$t</var>
			<text> </text>
			<text>=</text>
			<text> </text>
			<text>sprintf</text>
			<text>:</text>
			<text> </text>
			<text>pageid</text>
			<text>=</text>
			<var>8396</var>
			<text> </text>
			<text>textid</text>
			<text>=</text>
			<var>101</var>
			<text>,</text>
			<text> </text>
			<var>$t</var>
			<text>,</text>
			<text> </text>
			<var>null</var>
			<text>,</text>
			<text> </text>
			<var>null</var>
			<text>,</text>
			<text> </text>
			<var>null</var>
			<text>,</text>
			<text> </text>
			<var>null</var>
		</line>
		<line linenr="086" indent="&#160;&#160;&#160;&#160;&#160;&#160;&#160;&#160;">
			<text>display</text>
			<text> </text>
			<text>info</text>
			<text> </text>
			<text>box</text>
			<text>:</text>
			<text> </text>
			<text>text</text>
			<text>=</text>
			<text> </text>
			<var>$t</var>
			<text>,</text>
			<text> </text>
			<text>icon</text>
			<text>=</text>
			<text> </text>
			<var>66</var>
			<text>,</text>
			<text> </text>
			<text>timeout</text>
			<text>=</text>
			<text> </text>
			<var>5000</var>
			<text>,</text>
			<text> </text>
			<text>fadeout</text>
			<text>=</text>
			<text> </text>
			<var>1000</var>
		</line>
		<line linenr="087" indent="&#160;&#160;&#160;&#160;&#160;&#160;&#160;&#160;">
			<text>return</text>
			<text> </text>
			<var>null</var>
		</line>
		<line linenr="088" indent="&#160;&#160;&#160;&#160;&#160;&#160;&#160;">
			<text>else</text>
			<text> </text>
			<text>if</text>
			<text> </text>
			<var>$distance</var>
			<text> </text>
			<text>&gt;</text>
			<text> </text>
			<var>$requiredDistance</var>
		</line>
		<line linenr="089" indent="&#160;&#160;&#160;&#160;&#160;&#160;&#160;&#160;">
			<var>$t</var>
			<text> </text>
			<text>=</text>
			<text> </text>
			<text>'The target must be within a range of '</text>
			<text> </text>
			<text>+</text>
			<text> </text>
			<text>(</text>
			<var>$requiredDistance</var>
			<text> </text>
			<text>/</text>
			<text> </text>
			<var>1000</var>
			<text>)</text>
			<text> </text>
			<text>+</text>
			<text> </text>
			<text>' km'</text>
		</line>
		<line linenr="090" indent="&#160;&#160;&#160;&#160;&#160;&#160;&#160;&#160;">
			<var>$t</var>
			<text> </text>
			<text>=</text>
			<text> </text>
			<text>sprintf</text>
			<text>:</text>
			<text> </text>
			<text>pageid</text>
			<text>=</text>
			<var>8396</var>
			<text> </text>
			<text>textid</text>
			<text>=</text>
			<var>101</var>
			<text>,</text>
			<text> </text>
			<var>$t</var>
			<text>,</text>
			<text> </text>
			<var>null</var>
			<text>,</text>
			<text> </text>
			<var>null</var>
			<text>,</text>
			<text> </text>
			<var>null</var>
			<text>,</text>
			<text> </text>
			<var>null</var>
		</line>
		<line linenr="091" indent="&#160;&#160;&#160;&#160;&#160;&#160;&#160;&#160;">
			<text>display</text>
			<text> </text>
			<text>info</text>
			<text> </text>
			<text>box</text>
			<text>:</text>
			<text> </text>
			<text>text</text>
			<text>=</text>
			<text> </text>
			<var>$t</var>
			<text>,</text>
			<text> </text>
			<text>icon</text>
			<text>=</text>
			<text> </text>
			<var>66</var>
			<text>,</text>
			<text> </text>
			<text>timeout</text>
			<text>=</text>
			<text> </text>
			<var>5000</var>
			<text>,</text>
			<text> </text>
			<text>fadeout</text>
			<text>=</text>
			<text> </text>
			<var>1000</var>
		</line>
		<line linenr="092" indent="&#160;&#160;&#160;&#160;&#160;&#160;&#160;&#160;">
			<text>return</text>
			<text> </text>
			<var>null</var>
		</line>
		<line linenr="093" indent="&#160;&#160;&#160;&#160;&#160;&#160;&#160;">
			<text>else</text>
			<text> </text>
			<text>if</text>
			<text> </text>
			<text>not</text>
			<text> </text>
			<var>$exists</var>
		</line>
		<line linenr="094" indent="&#160;&#160;&#160;&#160;&#160;&#160;&#160;&#160;">
			<var>$t</var>
			<text> </text>
			<text>=</text>
			<text> </text>
			<text>sprintf</text>
			<text>:</text>
			<text> </text>
			<text>pageid</text>
			<text>=</text>
			<var>8396</var>
			<text> </text>
			<text>textid</text>
			<text>=</text>
			<var>101</var>
			<text>,</text>
			<text> </text>
			<text>'Invalid target'</text>
			<text>,</text>
			<text> </text>
			<var>null</var>
			<text>,</text>
			<text> </text>
			<var>null</var>
			<text>,</text>
			<text> </text>
			<var>null</var>
			<text>,</text>
			<text> </text>
			<var>null</var>
		</line>
		<line linenr="095" indent="&#160;&#160;&#160;&#160;&#160;&#160;&#160;&#160;">
			<text>display</text>
			<text> </text>
			<text>info</text>
			<text> </text>
			<text>box</text>
			<text>:</text>
			<text> </text>
			<text>text</text>
			<text>=</text>
			<text> </text>
			<var>$t</var>
			<text>,</text>
			<text> </text>
			<text>icon</text>
			<text>=</text>
			<text> </text>
			<var>66</var>
			<text>,</text>
			<text> </text>
			<text>timeout</text>
			<text>=</text>
			<text> </text>
			<var>5000</var>
			<text>,</text>
			<text> </text>
			<text>fadeout</text>
			<text>=</text>
			<text> </text>
			<var>1000</var>
		</line>
		<line linenr="096" indent="&#160;&#160;&#160;&#160;&#160;&#160;&#160;&#160;">
			<text>return</text>
			<text> </text>
			<var>null</var>
		</line>
		<line linenr="097" indent="&#160;&#160;&#160;&#160;&#160;&#160;&#160;">
			<text>end</text>
		</line>
		<line linenr="098" indent="&#160;&#160;&#160;&#160;&#160;&#160;&#160;" interruptable="@">
			<var>$expedition</var>
			<text> </text>
			<text>=</text>
			<text> </text>
			<var>$target</var>
			<text>-&gt;</text>
			<text> </text>
			<text>call</text>
			<text> </text>
			<text>script</text>
			<text> </text>
			<call>Mayhem.GenerateExpedition</call>
			<text> </text>
			<text>:</text>
			<text> </text>
			<text>squadNames</text>
			<text>=</text>
			<var>$squadNames</var>
			<text> </text>
			<text>riftDifficulty</text>
			<text>=</text>
			<var>0</var>
		</line>
		<line linenr="099" indent="&#160;&#160;&#160;&#160;&#160;&#160;&#160;">
			<text>if</text>
			<text> </text>
			<var>$expedition</var>
			<text> </text>
			<text>==</text>
			<text> </text>
			<var>null</var>
		</line>
		<line linenr="100" indent="&#160;&#160;&#160;&#160;&#160;&#160;&#160;&#160;">
			<var>$t</var>
			<text> </text>
			<text>=</text>
			<text> </text>
			<text>sprintf</text>
			<text>:</text>
			<text> </text>
			<text>pageid</text>
			<text>=</text>
			<var>8396</var>
			<text> </text>
			<text>textid</text>
			<text>=</text>
			<var>101</var>
			<text>,</text>
			<text> </text>
			<text>'Error, boarding aborted'</text>
			<text>,</text>
			<text> </text>
			<var>null</var>
			<text>,</text>
			<text> </text>
			<var>null</var>
			<text>,</text>
			<text> </text>
			<var>null</var>
			<text>,</text>
			<text> </text>
			<var>null</var>
		</line>
		<line linenr="101" indent="&#160;&#160;&#160;&#160;&#160;&#160;&#160;&#160;">
			<text>display</text>
			<text> </text>
			<text>info</text>
			<text> </text>
			<text>box</text>
			<text>:</text>
			<text> </text>
			<text>text</text>
			<text>=</text>
			<text> </text>
			<var>$t</var>
			<text>,</text>
			<text> </text>
			<text>icon</text>
			<text>=</text>
			<text> </text>
			<var>66</var>
			<text>,</text>
			<text> </text>
			<text>timeout</text>
			<text>=</text>
			<text> </text>
			<var>5000</var>
			<text>,</text>
			<text> </text>
			<text>fadeout</text>
			<text>=</text>
			<text> </text>
			<var>1000</var>
		</line>
		<line linenr="102" indent="&#160;&#160;&#160;&#160;&#160;&#160;&#160;&#160;">
			<text>return</text>
			<text> </text>
			<var>null</var>
		</line>
		<line linenr="103" indent="&#160;&#160;&#160;&#160;&#160;&#160;&#160;">
			<text>else</text>
		</line>
		<line linenr="104" indent="&#160;&#160;&#160;&#160;&#160;&#160;&#160;&#160;">
			<var>$physicalMarines</var>
			<text> </text>
			<text>=</text>
			<text> </text>
			<var>[THIS]</var>
			<text>-&gt;</text>
			<text> </text>
			<text>get</text>
			<text> </text>
			<text>marines</text>
			<text> </text>
			<text>array</text>
		</line>
		<line linenr="105" indent="&#160;&#160;&#160;&#160;&#160;&#160;&#160;&#160;">
			<var>$XS.Iterator1</var>
			<text> </text>
			<text>=</text>
			<text> </text>
			<text>size</text>
			<text> </text>
			<text>of</text>
			<text> </text>
			<text>array</text>
			<text> </text>
			<var>$physicalMarines</var>
		</line>
		<line linenr="106" indent="&#160;&#160;&#160;&#160;&#160;&#160;&#160;&#160;&#160;">
			<text>while</text>
			<text> </text>
			<var>$XS.Iterator1</var>
		</line>
		<line linenr="107" indent="&#160;&#160;&#160;&#160;&#160;&#160;&#160;&#160;&#160;">
			<text>dec</text>
			<text> </text>
			<var>$XS.Iterator1</var>
		</line>
		<line linenr="108" indent="&#160;&#160;&#160;&#160;&#160;&#160;&#160;&#160;&#160;&#160;">
			<var>$physicalMarine</var>
			<text> </text>
			<text>=</text>
			<text> </text>
			<var>$physicalMarines</var>
			<text>[</text>
			<var>$XS.Iterator1</var>
			<text>]</text>
		</line>
		<line linenr="109" indent="&#160;&#160;&#160;&#160;&#160;&#160;&#160;&#160;">
			<var>$name</var>
			<text> </text>
			<text>=</text>
			<text> </text>
			<var>$physicalMarine</var>
			<text>-&gt;</text>
			<text> </text>
			<text>get</text>
			<text> </text>
			<text>name</text>
		</line>
		<line linenr="110" indent="&#160;&#160;&#160;&#160;&#160;&#160;&#160;&#160;">
			<text>do</text>
			<text> </text>
			<text>if</text>
			<text> </text>
			<text>find</text>
			<text> </text>
			<var>$name</var>
			<text> </text>
			<text>in</text>
			<text> </text>
			<text>array</text>
			<text>:</text>
			<text> </text>
			<var>$squadNames</var>
		</line>
		<line linenr="111" indent="&#160;&#160;&#160;&#160;&#160;&#160;&#160;&#160;">
			<text>=</text>
			<text> </text>
			<var>$physicalMarine</var>
			<text>-&gt;</text>
			<text> </text>
			<text>destroy</text>
			<text> </text>
			<text>passenger</text>
		</line>
		<line linenr="112" indent="&#160;&#160;&#160;&#160;&#160;&#160;&#160;&#160;">
			<text>end</text>
		</line>
		<line linenr="113" indent="&#160;&#160;&#160;&#160;&#160;&#160;&#160;&#160;&#160;">
			<var>$t</var>
			<text> </text>
			<text>=</text>
			<text> </text>
			<text>sprintf</text>
			<text>:</text>
			<text> </text>
			<text>pageid</text>
			<text>=</text>
			<var>8396</var>
			<text> </text>
			<text>textid</text>
			<text>=</text>
			<var>102</var>
			<text>,</text>
			<text> </text>
			<text>'The team has been launched'</text>
			<text>,</text>
			<text> </text>
			<var>null</var>
			<text>,</text>
			<text> </text>
			<var>null</var>
			<text>,</text>
			<text> </text>
			<var>null</var>
			<text>,</text>
			<text> </text>
			<var>null</var>
		</line>
		<line linenr="114" indent="&#160;&#160;&#160;&#160;&#160;&#160;&#160;&#160;&#160;">
			<text>display</text>
			<text> </text>
			<text>info</text>
			<text> </text>
			<text>box</text>
			<text>:</text>
			<text> </text>
			<text>text</text>
			<text>=</text>
			<text> </text>
			<var>$t</var>
			<text>,</text>
			<text> </text>
			<text>icon</text>
			<text>=</text>
			<text> </text>
			<var>11</var>
			<text>,</text>
			<text> </text>
			<text>timeout</text>
			<text>=</text>
			<text> </text>
			<var>5000</var>
			<text>,</text>
			<text> </text>
			<text>fadeout</text>
			<text>=</text>
			<text> </text>
			<var>1000</var>
		</line>
		<line linenr="115" indent="&#160;&#160;&#160;&#160;&#160;&#160;&#160;&#160;&#160;">
			<text>if</text>
			<text> </text>
			<text>not</text>
			<text> </text>
			<text>get</text>
			<text> </text>
			<text>global</text>
			<text> </text>
			<text>variable</text>
			<text>:</text>
			<text> </text>
			<text>name</text>
			<text>=</text>
			<text>'mayhem_firstExpedition'</text>
		</line>
		<line linenr="116" indent="&#160;&#160;&#160;&#160;&#160;&#160;&#160;&#160;">
			<var>$t</var>
			<text> </text>
			<text>=</text>
			<text> </text>
			<text>read</text>
			<text> </text>
			<text>text</text>
			<text>:</text>
			<text> </text>
			<text>page</text>
			<text>=</text>
			<var>9972</var>
			<text> </text>
			<text>id</text>
			<text>=</text>
			<var>4212</var>
		</line>
		<line linenr="117" indent="&#160;&#160;&#160;&#160;&#160;&#160;&#160;&#160;">
			<var>[NULL]</var>
			<text>-&gt;</text>
			<text> </text>
			<text>send</text>
			<text> </text>
			<text>incoming</text>
			<text> </text>
			<text>message</text>
			<text>:</text>
			<text> </text>
			<text>text</text>
			<text>=</text>
			<var>$t</var>
			<text> </text>
			<text>temporary</text>
			<text>=</text>
			<var>[FALSE]</var>
		</line>
		<line linenr="118" indent="&#160;&#160;&#160;&#160;&#160;&#160;&#160;">
			<text>set</text>
			<text> </text>
			<text>global</text>
			<text> </text>
			<text>variable</text>
			<text>:</text>
			<text> </text>
			<text>name</text>
			<text>=</text>
			<text>'mayhem_firstExpedition'</text>
			<text> </text>
			<text>value</text>
			<text>=</text>
			<var>[TRUE]</var>
		</line>
		<line linenr="119" indent="&#160;&#160;&#160;&#160;&#160;&#160;">
			<text>end</text>
		</line>
		<line linenr="120" indent="&#160;&#160;&#160;&#160;&#160;">
			<text>return</text>
			<text> </text>
			<var>[TRUE]</var>
		</line>
		<line linenr="121" indent="&#160;&#160;&#160;&#160;&#160;&#160;">
			<text>end</text>
		</line>
		<line linenr="122" indent="&#160;&#160;&#160;&#160;&#160;&#160;">
			<text>end</text>
		</line>
		<line linenr="123" indent="&#160;&#160;&#160;&#160;&#160;&#160;">
			<text>else</text>
		</line>
		<line linenr="124" indent="&#160;&#160;&#160;&#160;&#160;">
			<var>$t</var>
			<text> </text>
			<text>=</text>
			<text> </text>
			<text>'The target shield must be lower than '</text>
			<text> </text>
			<text>+</text>
			<text> </text>
			<var>$requiredShield</var>
			<text> </text>
			<text>+</text>
			<text> </text>
			<text>'%'</text>
		</line>
		<line linenr="125" indent="&#160;&#160;&#160;&#160;">
			<var>$t</var>
			<text> </text>
			<text>=</text>
			<text> </text>
			<text>sprintf</text>
			<text>:</text>
			<text> </text>
			<text>pageid</text>
			<text>=</text>
			<var>8396</var>
			<text> </text>
			<text>textid</text>
			<text>=</text>
			<var>101</var>
			<text>,</text>
			<text> </text>
			<var>$t</var>
			<text>,</text>
			<text> </text>
			<var>null</var>
			<text>,</text>
			<text> </text>
			<var>null</var>
			<text>,</text>
			<text> </text>
			<var>null</var>
			<text>,</text>
			<text> </text>
			<var>null</var>
		</line>
		<line linenr="126" indent="&#160;&#160;&#160;&#160;&#160;">
			<text>display</text>
			<text> </text>
			<text>info</text>
			<text> </text>
			<text>box</text>
			<text>:</text>
			<text> </text>
			<text>text</text>
			<text>=</text>
			<text> </text>
			<var>$t</var>
			<text>,</text>
			<text> </text>
			<text>icon</text>
			<text>=</text>
			<text> </text>
			<var>66</var>
			<text>,</text>
			<text> </text>
			<text>timeout</text>
			<text>=</text>
			<text> </text>
			<var>5000</var>
			<text>,</text>
			<text> </text>
			<text>fadeout</text>
			<text>=</text>
			<text> </text>
			<var>1000</var>
		</line>
		<line linenr="127" indent="&#160;&#160;&#160;&#160;&#160;">
			<text>end</text>
		</line>
		<line linenr="128" indent="&#160;&#160;&#160;&#160;&#160;">
			<text>else</text>
		</line>
		<line linenr="129" indent="&#160;&#160;&#160;&#160;">
			<var>$t</var>
			<text> </text>
			<text>=</text>
			<text> </text>
			<text>'The target must be within a range of '</text>
			<text> </text>
			<text>+</text>
			<text> </text>
			<text>(</text>
			<var>$requiredDistance</var>
			<text> </text>
			<text>/</text>
			<text> </text>
			<var>1000</var>
			<text>)</text>
			<text> </text>
			<text>+</text>
			<text> </text>
			<text>' km'</text>
		</line>
		<line linenr="130" indent="&#160;&#160;&#160;">
			<var>$t</var>
			<text> </text>
			<text>=</text>
			<text> </text>
			<text>sprintf</text>
			<text>:</text>
			<text> </text>
			<text>pageid</text>
			<text>=</text>
			<var>8396</var>
			<text> </text>
			<text>textid</text>
			<text>=</text>
			<var>101</var>
			<text>,</text>
			<text> </text>
			<var>$t</var>
			<text>,</text>
			<text> </text>
			<var>null</var>
			<text>,</text>
			<text> </text>
			<var>null</var>
			<text>,</text>
			<text> </text>
			<var>null</var>
			<text>,</text>
			<text> </text>
			<var>null</var>
		</line>
		<line linenr="131" indent="&#160;&#160;&#160;&#160;">
			<text>display</text>
			<text> </text>
			<text>info</text>
			<text> </text>
			<text>box</text>
			<text>:</text>
			<text> </text>
			<text>text</text>
			<text>=</text>
			<text> </text>
			<var>$t</var>
			<text>,</text>
			<text> </text>
			<text>icon</text>
			<text>=</text>
			<text> </text>
			<var>66</var>
			<text>,</text>
			<text> </text>
			<text>timeout</text>
			<text>=</text>
			<text> </text>
			<var>5000</var>
			<text>,</text>
			<text> </text>
			<text>fadeout</text>
			<text>=</text>
			<text> </text>
			<var>1000</var>
		</line>
		<line linenr="132" indent="&#160;&#160;&#160;&#160;">
			<text>end</text>
		</line>
		<line linenr="133" indent="&#160;&#160;&#160;">
			<text>else</text>
		</line>
		<line linenr="134" indent="&#160;&#160;">
			<var>$t</var>
			<text> </text>
			<text>=</text>
			<text> </text>
			<text>sprintf</text>
			<text>:</text>
			<text> </text>
			<text>pageid</text>
			<text>=</text>
			<var>8396</var>
			<text> </text>
			<text>textid</text>
			<text>=</text>
			<var>101</var>
			<text>,</text>
			<text> </text>
			<text>'This ship is not an enemy'</text>
			<text>,</text>
			<text> </text>
			<var>null</var>
			<text>,</text>
			<text> </text>
			<var>null</var>
			<text>,</text>
			<text> </text>
			<var>null</var>
			<text>,</text>
			<text> </text>
			<var>null</var>
		</line>
		<line linenr="135" indent="&#160;&#160;&#160;">
			<text>display</text>
			<text> </text>
			<text>info</text>
			<text> </text>
			<text>box</text>
			<text>:</text>
			<text> </text>
			<text>text</text>
			<text>=</text>
			<text> </text>
			<var>$t</var>
			<text>,</text>
			<text> </text>
			<text>icon</text>
			<text>=</text>
			<text> </text>
			<var>66</var>
			<text>,</text>
			<text> </text>
			<text>timeout</text>
			<text>=</text>
			<text> </text>
			<var>5000</var>
			<text>,</text>
			<text> </text>
			<text>fadeout</text>
			<text>=</text>
			<text> </text>
			<var>1000</var>
		</line>
		<line linenr="136" indent="&#160;&#160;&#160;">
			<text>end</text>
		</line>
		<line linenr="137" indent="&#160;&#160;">
			<text>else</text>
		</line>
		<line linenr="138" indent="&#160;">
			<var>$t</var>
			<text> </text>
			<text>=</text>
			<text> </text>
			<text>sprintf</text>
			<text>:</text>
			<text> </text>
			<text>pageid</text>
			<text>=</text>
			<var>8396</var>
			<text> </text>
			<text>textid</text>
			<text>=</text>
			<var>101</var>
			<text>,</text>
			<text> </text>
			<text>'This ship cannot be boarded'</text>
			<text>,</text>
			<text> </text>
			<var>null</var>
			<text>,</text>
			<text> </text>
			<var>null</var>
			<text>,</text>
			<text> </text>
			<var>null</var>
			<text>,</text>
			<text> </text>
			<var>null</var>
		</line>
		<line linenr="139" indent="&#160;&#160;">
			<text>display</text>
			<text> </text>
			<text>info</text>
			<text> </text>
			<text>box</text>
			<text>:</text>
			<text> </text>
			<text>text</text>
			<text>=</text>
			<text> </text>
			<var>$t</var>
			<text>,</text>
			<text> </text>
			<text>icon</text>
			<text>=</text>
			<text> </text>
			<var>66</var>
			<text>,</text>
			<text> </text>
			<text>timeout</text>
			<text>=</text>
			<text> </text>
			<var>5000</var>
			<text>,</text>
			<text> </text>
			<text>fadeout</text>
			<text>=</text>
			<text> </text>
			<var>1000</var>
		</line>
		<line linenr="140" indent="&#160;&#160;">
			<text>end</text>
		</line>
		<line linenr="141" indent="&#160;">
			<text>else</text>
		</line>
		<line linenr="142" indent="">
			<var>$t</var>
			<text> </text>
			<text>=</text>
			<text> </text>
			<text>sprintf</text>
			<text>:</text>
			<text> </text>
			<text>pageid</text>
			<text>=</text>
			<var>8396</var>
			<text> </text>
			<text>textid</text>
			<text>=</text>
			<var>101</var>
			<text>,</text>
			<text> </text>
			<text>'A boarding operation is already in progress on this ship'</text>
			<text>,</text>
			<text> </text>
			<var>null</var>
			<text>,</text>
			<text> </text>
			<var>null</var>
			<text>,</text>
			<text> </text>
			<var>null</var>
			<text>,</text>
			<text> </text>
			<var>null</var>
		</line>
		<line linenr="143" indent="">
			<text>display</text>
			<text> </text>
			<text>info</text>
			<text> </text>
			<text>box</text>
			<text>:</text>
			<text> </text>
			<text>text</text>
			<text>=</text>
			<text> </text>
			<var>$t</var>
			<text>,</text>
			<text> </text>
			<text>icon</text>
			<text>=</text>
			<text> </text>
			<var>66</var>
			<text>,</text>
			<text> </text>
			<text>timeout</text>
			<text>=</text>
			<text> </text>
			<var>5000</var>
			<text>,</text>
			<text> </text>
			<text>fadeout</text>
			<text>=</text>
			<text> </text>
			<var>1000</var>
		</line>
		<line linenr="144" indent="">
			<text>end</text>
		</line>
		<line linenr="145" indent="">
			<text>end</text>
		</line>
		<line linenr="146" indent="" />
		<line linenr="147" indent="" />
		<line linenr="148" indent="">
			<text>return</text>
			<text> </text>
			<var>null</var>
		</line>
	</sourcetext>
	<codearray>
		<sval type="array" size="10">
			<sval type="string" val="!ship.cmd.boardship.preload" />
			<sval type="int" val="50" />
			<sval type="string" val="Ship Preload COMMAND ATTACK BOARDSHIP" />
			<sval type="int" val="3" />
			<sval type="int" val="0" />
			<sval type="array" size="26">
				<sval type="string" val="target" />
				<sval type="string" val="marines" />
				<sval type="string" val="t" />
				<sval type="string" val="hasTransporter" />
				<sval type="string" val="target.isBoardable" />
				<sval type="string" val="target.isBoardingDisabled" />
				<sval type="string" val="target.class" />
				<sval type="string" val="target.owner" />
				<sval type="string" val="relation" />
				<sval type="string" val="distance" />
				<sval type="string" val="shield" />
				<sval type="string" val="requiredShield" />
				<sval type="string" val="requiredDistance" />
				<sval type="string" val="expedition" />
				<sval type="string" val="squad" />
				<sval type="string" val="equipment" />
				<sval type="string" val="thisName" />
				<sval type="string" val="squadSize" />
				<sval type="string" val="squadNames" />
				<sval type="string" val="teleportation" />
				<sval type="string" val="targetSector" />
				<sval type="string" val="exists" />
				<sval type="string" val="physicalMarines" />
				<sval type="string" val="physicalMarine" />
				<sval type="string" val="XS.Iterator1" />
				<sval type="string" val="name" />
			</sval>
			<sval type="array" size="122">
				<sval type="array" size="4">
					<sval type="int" val="1433" />
					<sval type="int" val="131075" />
					<sval type="int" val="1" />
					<sval type="int" val="1" />
				</sval>
				<sval type="array" size="4">
					<sval type="int" val="131" />
					<sval type="int" val="1" />
					<sval type="int" val="131074" />
					<sval type="int" val="1" />
				</sval>
				<sval type="array" size="13">
					<sval type="int" val="104" />
					<sval type="int" val="-1610611197" />
					<sval type="int" val="3" />
					<sval type="int" val="131074" />
					<sval type="int" val="1" />
					<sval type="int" val="4" />
					<sval type="int" val="0" />
					<sval type="int" val="15" />
					<sval type="int" val="0" />
					<sval type="int" val="3" />
					<sval type="int" val="-1" />
					<sval type="int" val="0" />
					<sval type="int" val="-2" />
				</sval>
				<sval type="array" size="16">
					<sval type="int" val="150" />
					<sval type="int" val="2" />
					<sval type="int" val="4" />
					<sval type="int" val="8396" />
					<sval type="int" val="4" />
					<sval type="int" val="101" />
					<sval type="int" val="5" />
					<sval type="string" val="No marines onboard" />
					<sval type="int" val="0" />
					<sval type="int" val="0" />
					<sval type="int" val="0" />
					<sval type="int" val="0" />
					<sval type="int" val="0" />
					<sval type="int" val="0" />
					<sval type="int" val="0" />
					<sval type="int" val="0" />
				</sval>
				<sval type="array" size="9">
					<sval type="int" val="1861" />
					<sval type="int" val="131074" />
					<sval type="int" val="2" />
					<sval type="int" val="4" />
					<sval type="int" val="66" />
					<sval type="int" val="4" />
					<sval type="int" val="5000" />
					<sval type="int" val="4" />
					<sval type="int" val="1000" />
				</sval>
				<sval type="array" size="3">
					<sval type="int" val="103" />
					<sval type="int" val="0" />
					<sval type="int" val="0" />
				</sval>
				<sval type="array" size="4">
					<sval type="int" val="745" />
					<sval type="int" val="131075" />
					<sval type="int" val="1" />
					<sval type="int" val="-1610610173" />
				</sval>
				<sval type="array" size="16">
					<sval type="int" val="150" />
					<sval type="int" val="2" />
					<sval type="int" val="4" />
					<sval type="int" val="8396" />
					<sval type="int" val="4" />
					<sval type="int" val="101" />
					<sval type="int" val="5" />
					<sval type="string" val="Cannot launch marines while docked" />
					<sval type="int" val="0" />
					<sval type="int" val="0" />
					<sval type="int" val="0" />
					<sval type="int" val="0" />
					<sval type="int" val="0" />
					<sval type="int" val="0" />
					<sval type="int" val="0" />
					<sval type="int" val="0" />
				</sval>
				<sval type="array" size="9">
					<sval type="int" val="1861" />
					<sval type="int" val="131074" />
					<sval type="int" val="2" />
					<sval type="int" val="4" />
					<sval type="int" val="66" />
					<sval type="int" val="4" />
					<sval type="int" val="5000" />
					<sval type="int" val="4" />
					<sval type="int" val="1000" />
				</sval>
				<sval type="array" size="3">
					<sval type="int" val="103" />
					<sval type="int" val="0" />
					<sval type="int" val="0" />
				</sval>
				<sval type="array" size="6">
					<sval type="int" val="618" />
					<sval type="int" val="131075" />
					<sval type="int" val="1" />
					<sval type="int" val="3" />
					<sval type="int" val="9" />
					<sval type="int" val="1048610" />
				</sval>
				<sval type="array" size="10">
					<sval type="int" val="104" />
					<sval type="int" val="-1610608893" />
					<sval type="int" val="2" />
					<sval type="int" val="131074" />
					<sval type="int" val="3" />
					<sval type="int" val="15" />
					<sval type="int" val="65556" />
					<sval type="int" val="2" />
					<sval type="int" val="65556" />
					<sval type="int" val="-1" />
				</sval>
				<sval type="array" size="16">
					<sval type="int" val="150" />
					<sval type="int" val="2" />
					<sval type="int" val="4" />
					<sval type="int" val="8396" />
					<sval type="int" val="4" />
					<sval type="int" val="101" />
					<sval type="int" val="5" />
					<sval type="string" val="A Transporter Device is needed to initiate a boarding operation" />
					<sval type="int" val="0" />
					<sval type="int" val="0" />
					<sval type="int" val="0" />
					<sval type="int" val="0" />
					<sval type="int" val="0" />
					<sval type="int" val="0" />
					<sval type="int" val="0" />
					<sval type="int" val="0" />
				</sval>
				<sval type="array" size="9">
					<sval type="int" val="1861" />
					<sval type="int" val="131074" />
					<sval type="int" val="2" />
					<sval type="int" val="4" />
					<sval type="int" val="66" />
					<sval type="int" val="4" />
					<sval type="int" val="5000" />
					<sval type="int" val="4" />
					<sval type="int" val="1000" />
				</sval>
				<sval type="array" size="3">
					<sval type="int" val="103" />
					<sval type="int" val="0" />
					<sval type="int" val="0" />
				</sval>
				<sval type="array" size="25">
					<sval type="int" val="104" />
					<sval type="int" val="-1610608376" />
					<sval type="int" val="7" />
					<sval type="int" val="131074" />
					<sval type="int" val="0" />
					<sval type="int" val="131075" />
					<sval type="int" val="3" />
					<sval type="int" val="15" />
					<sval type="int" val="0" />
					<sval type="int" val="131075" />
					<sval type="int" val="1" />
					<sval type="int" val="131075" />
					<sval type="int" val="3" />
					<sval type="int" val="15" />
					<sval type="int" val="1" />
					<sval type="int" val="15" />
					<sval type="int" val="10" />
					<sval type="int" val="7" />
					<sval type="int" val="-1" />
					<sval type="int" val="0" />
					<sval type="int" val="-2" />
					<sval type="int" val="10" />
					<sval type="int" val="-4" />
					<sval type="int" val="1" />
					<sval type="int" val="-5" />
				</sval>
				<sval type="array" size="8">
					<sval type="int" val="1530" />
					<sval type="int" val="131075" />
					<sval type="int" val="1" />
					<sval type="int" val="0" />
					<sval type="int" val="24" />
					<sval type="int" val="21" />
					<sval type="int" val="5" />
					<sval type="string" val="Select a ship to board" />
				</sval>
				<sval type="array" size="4">
					<sval type="int" val="1432" />
					<sval type="int" val="131074" />
					<sval type="int" val="0" />
					<sval type="int" val="4" />
				</sval>
				<sval type="array" size="4">
					<sval type="int" val="1909" />
					<sval type="int" val="5" />
					<sval type="int" val="131074" />
					<sval type="int" val="0" />
				</sval>
				<sval type="array" size="4">
					<sval type="int" val="700" />
					<sval type="int" val="131074" />
					<sval type="int" val="0" />
					<sval type="int" val="6" />
				</sval>
				<sval type="array" size="4">
					<sval type="int" val="701" />
					<sval type="int" val="131074" />
					<sval type="int" val="0" />
					<sval type="int" val="7" />
				</sval>
				<sval type="array" size="6">
					<sval type="int" val="724" />
					<sval type="int" val="131074" />
					<sval type="int" val="0" />
					<sval type="int" val="8" />
					<sval type="int" val="10" />
					<sval type="int" val="10" />
				</sval>
				<sval type="array" size="6">
					<sval type="int" val="738" />
					<sval type="int" val="9" />
					<sval type="int" val="131075" />
					<sval type="int" val="1" />
					<sval type="int" val="131074" />
					<sval type="int" val="0" />
				</sval>
				<sval type="array" size="4">
					<sval type="int" val="901" />
					<sval type="int" val="131074" />
					<sval type="int" val="0" />
					<sval type="int" val="10" />
				</sval>
				<sval type="array" size="8">
					<sval type="int" val="102" />
					<sval type="string" val="Mayhem.IsImprovementUnlocked" />
					<sval type="int" val="-1610605821" />
					<sval type="int" val="131075" />
					<sval type="int" val="12" />
					<sval type="int" val="1" />
					<sval type="int" val="5" />
					<sval type="string" val="Shield expertise" />
				</sval>
				<sval type="array" size="7">
					<sval type="int" val="104" />
					<sval type="int" val="11" />
					<sval type="int" val="1" />
					<sval type="int" val="4" />
					<sval type="int" val="50" />
					<sval type="int" val="1" />
					<sval type="int" val="-1" />
				</sval>
				<sval type="array" size="2">
					<sval type="int" val="112" />
					<sval type="int" val="28" />
				</sval>
				<sval type="array" size="7">
					<sval type="int" val="104" />
					<sval type="int" val="11" />
					<sval type="int" val="1" />
					<sval type="int" val="4" />
					<sval type="int" val="10" />
					<sval type="int" val="1" />
					<sval type="int" val="-1" />
				</sval>
				<sval type="array" size="2">
					<sval type="int" val="1343" />
					<sval type="int" val="12" />
				</sval>
				<sval type="array" size="4">
					<sval type="int" val="706" />
					<sval type="int" val="131074" />
					<sval type="int" val="0" />
					<sval type="int" val="-1610581757" />
				</sval>
				<sval type="array" size="6">
					<sval type="int" val="156" />
					<sval type="int" val="131074" />
					<sval type="int" val="0" />
					<sval type="int" val="5" />
					<sval type="string" val="mayhem_expedition" />
					<sval type="int" val="13" />
				</sval>
				<sval type="array" size="6">
					<sval type="int" val="1709" />
					<sval type="int" val="-536840444" />
					<sval type="int" val="131074" />
					<sval type="int" val="13" />
					<sval type="int" val="5" />
					<sval type="string" val="inProgress" />
				</sval>
				<sval type="array" size="16">
					<sval type="int" val="104" />
					<sval type="int" val="-1610583037" />
					<sval type="int" val="4" />
					<sval type="int" val="131074" />
					<sval type="int" val="4" />
					<sval type="int" val="131074" />
					<sval type="int" val="5" />
					<sval type="int" val="15" />
					<sval type="int" val="65556" />
					<sval type="int" val="15" />
					<sval type="int" val="9" />
					<sval type="int" val="4" />
					<sval type="int" val="-1" />
					<sval type="int" val="9" />
					<sval type="int" val="65556" />
					<sval type="int" val="-2" />
				</sval>
				<sval type="array" size="13">
					<sval type="int" val="104" />
					<sval type="int" val="-1610583805" />
					<sval type="int" val="3" />
					<sval type="int" val="131074" />
					<sval type="int" val="8" />
					<sval type="int" val="14" />
					<sval type="int" val="-1" />
					<sval type="int" val="15" />
					<sval type="int" val="0" />
					<sval type="int" val="3" />
					<sval type="int" val="-1" />
					<sval type="int" val="0" />
					<sval type="int" val="-2" />
				</sval>
				<sval type="array" size="13">
					<sval type="int" val="104" />
					<sval type="int" val="-1610584829" />
					<sval type="int" val="3" />
					<sval type="int" val="131074" />
					<sval type="int" val="9" />
					<sval type="int" val="131074" />
					<sval type="int" val="12" />
					<sval type="int" val="15" />
					<sval type="int" val="5" />
					<sval type="int" val="3" />
					<sval type="int" val="-1" />
					<sval type="int" val="5" />
					<sval type="int" val="-2" />
				</sval>
				<sval type="array" size="13">
					<sval type="int" val="104" />
					<sval type="int" val="-1610585853" />
					<sval type="int" val="3" />
					<sval type="int" val="131074" />
					<sval type="int" val="10" />
					<sval type="int" val="131074" />
					<sval type="int" val="11" />
					<sval type="int" val="15" />
					<sval type="int" val="3" />
					<sval type="int" val="3" />
					<sval type="int" val="-1" />
					<sval type="int" val="3" />
					<sval type="int" val="-2" />
				</sval>
				<sval type="array" size="4">
					<sval type="int" val="128" />
					<sval type="int" val="14" />
					<sval type="int" val="4" />
					<sval type="int" val="0" />
				</sval>
				<sval type="array" size="4">
					<sval type="int" val="158" />
					<sval type="int" val="5" />
					<sval type="string" val="mayhem_marines" />
					<sval type="int" val="1" />
				</sval>
				<sval type="array" size="4">
					<sval type="int" val="158" />
					<sval type="int" val="5" />
					<sval type="string" val="mayhem_equipment" />
					<sval type="int" val="15" />
				</sval>
				<sval type="array" size="4">
					<sval type="int" val="1028" />
					<sval type="int" val="131075" />
					<sval type="int" val="1" />
					<sval type="int" val="16" />
				</sval>
				<sval type="array" size="8">
					<sval type="int" val="102" />
					<sval type="string" val="Mayhem.GetShipSquadSize" />
					<sval type="int" val="17" />
					<sval type="int" val="131075" />
					<sval type="int" val="12" />
					<sval type="int" val="1" />
					<sval type="int" val="131074" />
					<sval type="int" val="6" />
				</sval>
				<sval type="array" size="12">
					<sval type="int" val="102" />
					<sval type="string" val="Menu.BoardingPreload" />
					<sval type="int" val="18" />
					<sval type="int" val="131075" />
					<sval type="int" val="12" />
					<sval type="int" val="3" />
					<sval type="int" val="131075" />
					<sval type="int" val="1" />
					<sval type="int" val="131074" />
					<sval type="int" val="0" />
					<sval type="int" val="131074" />
					<sval type="int" val="17" />
				</sval>
				<sval type="array" size="6">
					<sval type="int" val="125" />
					<sval type="int" val="-1610586109" />
					<sval type="int" val="131074" />
					<sval type="int" val="18" />
					<sval type="int" val="20" />
					<sval type="int" val="21" />
				</sval>
				<sval type="array" size="7">
					<sval type="int" val="104" />
					<sval type="int" val="19" />
					<sval type="int" val="1" />
					<sval type="int" val="4" />
					<sval type="int" val="3" />
					<sval type="int" val="1" />
					<sval type="int" val="-1" />
				</sval>
				<sval type="array" size="7">
					<sval type="int" val="104" />
					<sval type="int" val="-1610598135" />
					<sval type="int" val="1" />
					<sval type="int" val="131074" />
					<sval type="int" val="19" />
					<sval type="int" val="1" />
					<sval type="int" val="-1" />
				</sval>
				<sval type="array" size="4">
					<sval type="int" val="703" />
					<sval type="int" val="131074" />
					<sval type="int" val="0" />
					<sval type="int" val="20" />
				</sval>
				<sval type="array" size="13">
					<sval type="int" val="104" />
					<sval type="int" val="-1610600189" />
					<sval type="int" val="3" />
					<sval type="int" val="131074" />
					<sval type="int" val="20" />
					<sval type="int" val="131075" />
					<sval type="int" val="6" />
					<sval type="int" val="15" />
					<sval type="int" val="1" />
					<sval type="int" val="3" />
					<sval type="int" val="-1" />
					<sval type="int" val="1" />
					<sval type="int" val="-2" />
				</sval>
				<sval type="array" size="9">
					<sval type="int" val="1861" />
					<sval type="int" val="5" />
					<sval type="string" val="Boarding operation aborted" />
					<sval type="int" val="4" />
					<sval type="int" val="0" />
					<sval type="int" val="4" />
					<sval type="int" val="5000" />
					<sval type="int" val="4" />
					<sval type="int" val="1000" />
				</sval>
				<sval type="array" size="3">
					<sval type="int" val="103" />
					<sval type="int" val="0" />
					<sval type="int" val="0" />
				</sval>
				<sval type="array" size="13">
					<sval type="int" val="104" />
					<sval type="int" val="-1610599421" />
					<sval type="int" val="3" />
					<sval type="int" val="131074" />
					<sval type="int" val="19" />
					<sval type="int" val="4" />
					<sval type="int" val="1" />
					<sval type="int" val="15" />
					<sval type="int" val="0" />
					<sval type="int" val="3" />
					<sval type="int" val="-1" />
					<sval type="int" val="0" />
					<sval type="int" val="-2" />
				</sval>
				<sval type="array" size="19">
					<sval type="int" val="104" />
					<sval type="int" val="2" />
					<sval type="int" val="5" />
					<sval type="int" val="5" />
					<sval type="string" val="Launching team in " />
					<sval type="int" val="131074" />
					<sval type="int" val="19" />
					<sval type="int" val="15" />
					<sval type="int" val="11" />
					<sval type="int" val="5" />
					<sval type="string" val=" second" />
					<sval type="int" val="15" />
					<sval type="int" val="11" />
					<sval type="int" val="5" />
					<sval type="int" val="-1" />
					<sval type="int" val="11" />
					<sval type="int" val="-2" />
					<sval type="int" val="11" />
					<sval type="int" val="-4" />
				</sval>
				<sval type="array" size="2">
					<sval type="int" val="112" />
					<sval type="int" val="53" />
				</sval>
				<sval type="array" size="19">
					<sval type="int" val="104" />
					<sval type="int" val="2" />
					<sval type="int" val="5" />
					<sval type="int" val="5" />
					<sval type="string" val="Launching team in " />
					<sval type="int" val="131074" />
					<sval type="int" val="19" />
					<sval type="int" val="15" />
					<sval type="int" val="11" />
					<sval type="int" val="5" />
					<sval type="string" val=" seconds" />
					<sval type="int" val="15" />
					<sval type="int" val="11" />
					<sval type="int" val="5" />
					<sval type="int" val="-1" />
					<sval type="int" val="11" />
					<sval type="int" val="-2" />
					<sval type="int" val="11" />
					<sval type="int" val="-4" />
				</sval>
				<sval type="array" size="9">
					<sval type="int" val="1861" />
					<sval type="int" val="131074" />
					<sval type="int" val="2" />
					<sval type="int" val="4" />
					<sval type="int" val="0" />
					<sval type="int" val="4" />
					<sval type="int" val="1500" />
					<sval type="int" val="4" />
					<sval type="int" val="1000" />
				</sval>
				<sval type="array" size="2">
					<sval type="int" val="143" />
					<sval type="int" val="19" />
				</sval>
				<sval type="array" size="4">
					<sval type="int" val="105" />
					<sval type="int" val="-2147483647" />
					<sval type="int" val="4" />
					<sval type="int" val="1000" />
				</sval>
				<sval type="array" size="2">
					<sval type="int" val="112" />
					<sval type="int" val="44" />
				</sval>
				<sval type="array" size="4">
					<sval type="int" val="901" />
					<sval type="int" val="131074" />
					<sval type="int" val="0" />
					<sval type="int" val="10" />
				</sval>
				<sval type="array" size="6">
					<sval type="int" val="738" />
					<sval type="int" val="9" />
					<sval type="int" val="131074" />
					<sval type="int" val="0" />
					<sval type="int" val="131075" />
					<sval type="int" val="1" />
				</sval>
				<sval type="array" size="4">
					<sval type="int" val="706" />
					<sval type="int" val="131074" />
					<sval type="int" val="0" />
					<sval type="int" val="21" />
				</sval>
				<sval type="array" size="6">
					<sval type="int" val="156" />
					<sval type="int" val="131074" />
					<sval type="int" val="0" />
					<sval type="int" val="5" />
					<sval type="string" val="mayhem_expedition" />
					<sval type="int" val="13" />
				</sval>
				<sval type="array" size="6">
					<sval type="int" val="1709" />
					<sval type="int" val="-1610595837" />
					<sval type="int" val="131074" />
					<sval type="int" val="13" />
					<sval type="int" val="5" />
					<sval type="string" val="inProgress" />
				</sval>
				<sval type="array" size="16">
					<sval type="int" val="150" />
					<sval type="int" val="2" />
					<sval type="int" val="4" />
					<sval type="int" val="8396" />
					<sval type="int" val="4" />
					<sval type="int" val="101" />
					<sval type="int" val="5" />
					<sval type="string" val="A boarding operation is already in progress on this ship" />
					<sval type="int" val="0" />
					<sval type="int" val="0" />
					<sval type="int" val="0" />
					<sval type="int" val="0" />
					<sval type="int" val="0" />
					<sval type="int" val="0" />
					<sval type="int" val="0" />
					<sval type="int" val="0" />
				</sval>
				<sval type="array" size="9">
					<sval type="int" val="1861" />
					<sval type="int" val="131074" />
					<sval type="int" val="2" />
					<sval type="int" val="4" />
					<sval type="int" val="66" />
					<sval type="int" val="4" />
					<sval type="int" val="5000" />
					<sval type="int" val="4" />
					<sval type="int" val="1000" />
				</sval>
				<sval type="array" size="3">
					<sval type="int" val="103" />
					<sval type="int" val="0" />
					<sval type="int" val="0" />
				</sval>
				<sval type="array" size="2">
					<sval type="int" val="112" />
					<sval type="int" val="82" />
				</sval>
				<sval type="array" size="13">
					<sval type="int" val="104" />
					<sval type="int" val="-1610594299" />
					<sval type="int" val="3" />
					<sval type="int" val="131074" />
					<sval type="int" val="10" />
					<sval type="int" val="131074" />
					<sval type="int" val="11" />
					<sval type="int" val="15" />
					<sval type="int" val="4" />
					<sval type="int" val="3" />
					<sval type="int" val="-1" />
					<sval type="int" val="4" />
					<sval type="int" val="-2" />
				</sval>
				<sval type="array" size="19">
					<sval type="int" val="104" />
					<sval type="int" val="2" />
					<sval type="int" val="5" />
					<sval type="int" val="5" />
					<sval type="string" val="The target shield must be lower than " />
					<sval type="int" val="131074" />
					<sval type="int" val="11" />
					<sval type="int" val="15" />
					<sval type="int" val="11" />
					<sval type="int" val="5" />
					<sval type="string" val="%" />
					<sval type="int" val="15" />
					<sval type="int" val="11" />
					<sval type="int" val="5" />
					<sval type="int" val="-1" />
					<sval type="int" val="11" />
					<sval type="int" val="-2" />
					<sval type="int" val="11" />
					<sval type="int" val="-4" />
				</sval>
				<sval type="array" size="16">
					<sval type="int" val="150" />
					<sval type="int" val="2" />
					<sval type="int" val="4" />
					<sval type="int" val="8396" />
					<sval type="int" val="4" />
					<sval type="int" val="101" />
					<sval type="int" val="131074" />
					<sval type="int" val="2" />
					<sval type="int" val="0" />
					<sval type="int" val="0" />
					<sval type="int" val="0" />
					<sval type="int" val="0" />
					<sval type="int" val="0" />
					<sval type="int" val="0" />
					<sval type="int" val="0" />
					<sval type="int" val="0" />
				</sval>
				<sval type="array" size="9">
					<sval type="int" val="1861" />
					<sval type="int" val="131074" />
					<sval type="int" val="2" />
					<sval type="int" val="4" />
					<sval type="int" val="66" />
					<sval type="int" val="4" />
					<sval type="int" val="5000" />
					<sval type="int" val="4" />
					<sval type="int" val="1000" />
				</sval>
				<sval type="array" size="3">
					<sval type="int" val="103" />
					<sval type="int" val="0" />
					<sval type="int" val="0" />
				</sval>
				<sval type="array" size="2">
					<sval type="int" val="112" />
					<sval type="int" val="82" />
				</sval>
				<sval type="array" size="13">
					<sval type="int" val="104" />
					<sval type="int" val="-1610592763" />
					<sval type="int" val="3" />
					<sval type="int" val="131074" />
					<sval type="int" val="9" />
					<sval type="int" val="131074" />
					<sval type="int" val="12" />
					<sval type="int" val="15" />
					<sval type="int" val="2" />
					<sval type="int" val="3" />
					<sval type="int" val="-1" />
					<sval type="int" val="2" />
					<sval type="int" val="-2" />
				</sval>
				<sval type="array" size="27">
					<sval type="int" val="104" />
					<sval type="int" val="2" />
					<sval type="int" val="7" />
					<sval type="int" val="5" />
					<sval type="string" val="The target must be within a range of " />
					<sval type="int" val="131074" />
					<sval type="int" val="12" />
					<sval type="int" val="4" />
					<sval type="int" val="1000" />
					<sval type="int" val="15" />
					<sval type="int" val="14" />
					<sval type="int" val="15" />
					<sval type="int" val="11" />
					<sval type="int" val="5" />
					<sval type="string" val=" km" />
					<sval type="int" val="15" />
					<sval type="int" val="11" />
					<sval type="int" val="9" />
					<sval type="int" val="-1" />
					<sval type="int" val="11" />
					<sval type="int" val="16" />
					<sval type="int" val="-2" />
					<sval type="int" val="14" />
					<sval type="int" val="-3" />
					<sval type="int" val="17" />
					<sval type="int" val="11" />
					<sval type="int" val="-6" />
				</sval>
				<sval type="array" size="16">
					<sval type="int" val="150" />
					<sval type="int" val="2" />
					<sval type="int" val="4" />
					<sval type="int" val="8396" />
					<sval type="int" val="4" />
					<sval type="int" val="101" />
					<sval type="int" val="131074" />
					<sval type="int" val="2" />
					<sval type="int" val="0" />
					<sval type="int" val="0" />
					<sval type="int" val="0" />
					<sval type="int" val="0" />
					<sval type="int" val="0" />
					<sval type="int" val="0" />
					<sval type="int" val="0" />
					<sval type="int" val="0" />
				</sval>
				<sval type="array" size="9">
					<sval type="int" val="1861" />
					<sval type="int" val="131074" />
					<sval type="int" val="2" />
					<sval type="int" val="4" />
					<sval type="int" val="66" />
					<sval type="int" val="4" />
					<sval type="int" val="5000" />
					<sval type="int" val="4" />
					<sval type="int" val="1000" />
				</sval>
				<sval type="array" size="3">
					<sval type="int" val="103" />
					<sval type="int" val="0" />
					<sval type="int" val="0" />
				</sval>
				<sval type="array" size="2">
					<sval type="int" val="112" />
					<sval type="int" val="82" />
				</sval>
				<sval type="array" size="7">
					<sval type="int" val="104" />
					<sval type="int" val="-536849914" />
					<sval type="int" val="1" />
					<sval type="int" val="131074" />
					<sval type="int" val="21" />
					<sval type="int" val="1" />
					<sval type="int" val="-1" />
				</sval>
				<sval type="array" size="16">
					<sval type="int" val="150" />
					<sval type="int" val="2" />
					<sval type="int" val="4" />
					<sval type="int" val="8396" />
					<sval type="int" val="4" />
					<sval type="int" val="101" />
					<sval type="int" val="5" />
					<sval type="string" val="Invalid target" />
					<sval type="int" val="0" />
					<sval type="int" val="0" />
					<sval type="int" val="0" />
					<sval type="int" val="0" />
					<sval type="int" val="0" />
					<sval type="int" val="0" />
					<sval type="int" val="0" />
					<sval type="int" val="0" />
				</sval>
				<sval type="array" size="9">
					<sval type="int" val="1861" />
					<sval type="int" val="131074" />
					<sval type="int" val="2" />
					<sval type="int" val="4" />
					<sval type="int" val="66" />
					<sval type="int" val="4" />
					<sval type="int" val="5000" />
					<sval type="int" val="4" />
					<sval type="int" val="1000" />
				</sval>
				<sval type="array" size="3">
					<sval type="int" val="103" />
					<sval type="int" val="0" />
					<sval type="int" val="0" />
				</sval>
				<sval type="array" size="10">
					<sval type="int" val="102" />
					<sval type="string" val="Mayhem.GenerateExpedition" />
					<sval type="int" val="13" />
					<sval type="int" val="131074" />
					<sval type="int" val="0" />
					<sval type="int" val="2" />
					<sval type="int" val="131074" />
					<sval type="int" val="18" />
					<sval type="int" val="4" />
					<sval type="int" val="0" />
				</sval>
				<sval type="array" size="13">
					<sval type="int" val="104" />
					<sval type="int" val="-1610590205" />
					<sval type="int" val="3" />
					<sval type="int" val="131074" />
					<sval type="int" val="13" />
					<sval type="int" val="0" />
					<sval type="int" val="0" />
					<sval type="int" val="15" />
					<sval type="int" val="0" />
					<sval type="int" val="3" />
					<sval type="int" val="-1" />
					<sval type="int" val="0" />
					<sval type="int" val="-2" />
				</sval>
				<sval type="array" size="16">
					<sval type="int" val="150" />
					<sval type="int" val="2" />
					<sval type="int" val="4" />
					<sval type="int" val="8396" />
					<sval type="int" val="4" />
					<sval type="int" val="101" />
					<sval type="int" val="5" />
					<sval type="string" val="Error, boarding aborted" />
					<sval type="int" val="0" />
					<sval type="int" val="0" />
					<sval type="int" val="0" />
					<sval type="int" val="0" />
					<sval type="int" val="0" />
					<sval type="int" val="0" />
					<sval type="int" val="0" />
					<sval type="int" val="0" />
				</sval>
				<sval type="array" size="9">
					<sval type="int" val="1861" />
					<sval type="int" val="131074" />
					<sval type="int" val="2" />
					<sval type="int" val="4" />
					<sval type="int" val="66" />
					<sval type="int" val="4" />
					<sval type="int" val="5000" />
					<sval type="int" val="4" />
					<sval type="int" val="1000" />
				</sval>
				<sval type="array" size="3">
					<sval type="int" val="103" />
					<sval type="int" val="0" />
					<sval type="int" val="0" />
				</sval>
				<sval type="array" size="2">
					<sval type="int" val="112" />
					<sval type="int" val="104" />
				</sval>
				<sval type="array" size="4">
					<sval type="int" val="1433" />
					<sval type="int" val="131075" />
					<sval type="int" val="1" />
					<sval type="int" val="22" />
				</sval>
				<sval type="array" size="4">
					<sval type="int" val="131" />
					<sval type="int" val="24" />
					<sval type="int" val="131074" />
					<sval type="int" val="22" />
				</sval>
				<sval type="array" size="7">
					<sval type="int" val="104" />
					<sval type="int" val="-1610587895" />
					<sval type="int" val="1" />
					<sval type="int" val="131074" />
					<sval type="int" val="24" />
					<sval type="int" val="1" />
					<sval type="int" val="-1" />
				</sval>
				<sval type="array" size="2">
					<sval type="int" val="143" />
					<sval type="int" val="24" />
				</sval>
				<sval type="array" size="6">
					<sval type="int" val="129" />
					<sval type="int" val="23" />
					<sval type="int" val="131074" />
					<sval type="int" val="22" />
					<sval type="int" val="131074" />
					<sval type="int" val="24" />
				</sval>
				<sval type="array" size="4">
					<sval type="int" val="1028" />
					<sval type="int" val="131074" />
					<sval type="int" val="23" />
					<sval type="int" val="25" />
				</sval>
				<sval type="array" size="6">
					<sval type="int" val="1406" />
					<sval type="int" val="-1610588152" />
					<sval type="int" val="131074" />
					<sval type="int" val="25" />
					<sval type="int" val="131074" />
					<sval type="int" val="18" />
				</sval>
				<sval type="array" size="4">
					<sval type="int" val="1237" />
					<sval type="int" val="131074" />
					<sval type="int" val="23" />
					<sval type="int" val="-2147483647" />
				</sval>
				<sval type="array" size="2">
					<sval type="int" val="112" />
					<sval type="int" val="90" />
				</sval>
				<sval type="array" size="16">
					<sval type="int" val="150" />
					<sval type="int" val="2" />
					<sval type="int" val="4" />
					<sval type="int" val="8396" />
					<sval type="int" val="4" />
					<sval type="int" val="102" />
					<sval type="int" val="5" />
					<sval type="string" val="The team has been launched" />
					<sval type="int" val="0" />
					<sval type="int" val="0" />
					<sval type="int" val="0" />
					<sval type="int" val="0" />
					<sval type="int" val="0" />
					<sval type="int" val="0" />
					<sval type="int" val="0" />
					<sval type="int" val="0" />
				</sval>
				<sval type="array" size="9">
					<sval type="int" val="1861" />
					<sval type="int" val="131074" />
					<sval type="int" val="2" />
					<sval type="int" val="4" />
					<sval type="int" val="11" />
					<sval type="int" val="4" />
					<sval type="int" val="5000" />
					<sval type="int" val="4" />
					<sval type="int" val="1000" />
				</sval>
				<sval type="array" size="4">
					<sval type="int" val="158" />
					<sval type="int" val="5" />
					<sval type="string" val="mayhem_firstExpedition" />
					<sval type="int" val="-536844540" />
				</sval>
				<sval type="array" size="6">
					<sval type="int" val="126" />
					<sval type="int" val="2" />
					<sval type="int" val="4" />
					<sval type="int" val="9972" />
					<sval type="int" val="4" />
					<sval type="int" val="4212" />
				</sval>
				<sval type="array" size="7">
					<sval type="int" val="1215" />
					<sval type="int" val="131075" />
					<sval type="int" val="12" />
					<sval type="int" val="131074" />
					<sval type="int" val="2" />
					<sval type="int" val="131075" />
					<sval type="int" val="9" />
				</sval>
				<sval type="array" size="5">
					<sval type="int" val="157" />
					<sval type="int" val="5" />
					<sval type="string" val="mayhem_firstExpedition" />
					<sval type="int" val="131075" />
					<sval type="int" val="10" />
				</sval>
				<sval type="array" size="3">
					<sval type="int" val="103" />
					<sval type="int" val="131075" />
					<sval type="int" val="10" />
				</sval>
				<sval type="array" size="2">
					<sval type="int" val="112" />
					<sval type="int" val="108" />
				</sval>
				<sval type="array" size="19">
					<sval type="int" val="104" />
					<sval type="int" val="2" />
					<sval type="int" val="5" />
					<sval type="int" val="5" />
					<sval type="string" val="The target shield must be lower than " />
					<sval type="int" val="131074" />
					<sval type="int" val="11" />
					<sval type="int" val="15" />
					<sval type="int" val="11" />
					<sval type="int" val="5" />
					<sval type="string" val="%" />
					<sval type="int" val="15" />
					<sval type="int" val="11" />
					<sval type="int" val="5" />
					<sval type="int" val="-1" />
					<sval type="int" val="11" />
					<sval type="int" val="-2" />
					<sval type="int" val="11" />
					<sval type="int" val="-4" />
				</sval>
				<sval type="array" size="16">
					<sval type="int" val="150" />
					<sval type="int" val="2" />
					<sval type="int" val="4" />
					<sval type="int" val="8396" />
					<sval type="int" val="4" />
					<sval type="int" val="101" />
					<sval type="int" val="131074" />
					<sval type="int" val="2" />
					<sval type="int" val="0" />
					<sval type="int" val="0" />
					<sval type="int" val="0" />
					<sval type="int" val="0" />
					<sval type="int" val="0" />
					<sval type="int" val="0" />
					<sval type="int" val="0" />
					<sval type="int" val="0" />
				</sval>
				<sval type="array" size="9">
					<sval type="int" val="1861" />
					<sval type="int" val="131074" />
					<sval type="int" val="2" />
					<sval type="int" val="4" />
					<sval type="int" val="66" />
					<sval type="int" val="4" />
					<sval type="int" val="5000" />
					<sval type="int" val="4" />
					<sval type="int" val="1000" />
				</sval>
				<sval type="array" size="2">
					<sval type="int" val="112" />
					<sval type="int" val="112" />
				</sval>
				<sval type="array" size="27">
					<sval type="int" val="104" />
					<sval type="int" val="2" />
					<sval type="int" val="7" />
					<sval type="int" val="5" />
					<sval type="string" val="The target must be within a range of " />
					<sval type="int" val="131074" />
					<sval type="int" val="12" />
					<sval type="int" val="4" />
					<sval type="int" val="1000" />
					<sval type="int" val="15" />
					<sval type="int" val="14" />
					<sval type="int" val="15" />
					<sval type="int" val="11" />
					<sval type="int" val="5" />
					<sval type="string" val=" km" />
					<sval type="int" val="15" />
					<sval type="int" val="11" />
					<sval type="int" val="9" />
					<sval type="int" val="-1" />
					<sval type="int" val="11" />
					<sval type="int" val="16" />
					<sval type="int" val="-2" />
					<sval type="int" val="14" />
					<sval type="int" val="-3" />
					<sval type="int" val="17" />
					<sval type="int" val="11" />
					<sval type="int" val="-6" />
				</sval>
				<sval type="array" size="16">
					<sval type="int" val="150" />
					<sval type="int" val="2" />
					<sval type="int" val="4" />
					<sval type="int" val="8396" />
					<sval type="int" val="4" />
					<sval type="int" val="101" />
					<sval type="int" val="131074" />
					<sval type="int" val="2" />
					<sval type="int" val="0" />
					<sval type="int" val="0" />
					<sval type="int" val="0" />
					<sval type="int" val="0" />
					<sval type="int" val="0" />
					<sval type="int" val="0" />
					<sval type="int" val="0" />
					<sval type="int" val="0" />
				</sval>
				<sval type="array" size="9">
					<sval type="int" val="1861" />
					<sval type="int" val="131074" />
					<sval type="int" val="2" />
					<sval type="int" val="4" />
					<sval type="int" val="66" />
					<sval type="int" val="4" />
					<sval type="int" val="5000" />
					<sval type="int" val="4" />
					<sval type="int" val="1000" />
				</sval>
				<sval type="array" size="2">
					<sval type="int" val="112" />
					<sval type="int" val="115" />
				</sval>
				<sval type="array" size="16">
					<sval type="int" val="150" />
					<sval type="int" val="2" />
					<sval type="int" val="4" />
					<sval type="int" val="8396" />
					<sval type="int" val="4" />
					<sval type="int" val="101" />
					<sval type="int" val="5" />
					<sval type="string" val="This ship is not an enemy" />
					<sval type="int" val="0" />
					<sval type="int" val="0" />
					<sval type="int" val="0" />
					<sval type="int" val="0" />
					<sval type="int" val="0" />
					<sval type="int" val="0" />
					<sval type="int" val="0" />
					<sval type="int" val="0" />
				</sval>
				<sval type="array" size="9">
					<sval type="int" val="1861" />
					<sval type="int" val="131074" />
					<sval type="int" val="2" />
					<sval type="int" val="4" />
					<sval type="int" val="66" />
					<sval type="int" val="4" />
					<sval type="int" val="5000" />
					<sval type="int" val="4" />
					<sval type="int" val="1000" />
				</sval>
				<sval type="array" size="2">
					<sval type="int" val="112" />
					<sval type="int" val="118" />
				</sval>
				<sval type="array" size="16">
					<sval type="int" val="150" />
					<sval type="int" val="2" />
					<sval type="int" val="4" />
					<sval type="int" val="8396" />
					<sval type="int" val="4" />
					<sval type="int" val="101" />
					<sval type="int" val="5" />
					<sval type="string" val="This ship cannot be boarded" />
					<sval type="int" val="0" />
					<sval type="int" val="0" />
					<sval type="int" val="0" />
					<sval type="int" val="0" />
					<sval type="int" val="0" />
					<sval type="int" val="0" />
					<sval type="int" val="0" />
					<sval type="int" val="0" />
				</sval>
				<sval type="array" size="9">
					<sval type="int" val="1861" />
					<sval type="int" val="131074" />
					<sval type="int" val="2" />
					<sval type="int" val="4" />
					<sval type="int" val="66" />
					<sval type="int" val="4" />
					<sval type="int" val="5000" />
					<sval type="int" val="4" />
					<sval type="int" val="1000" />
				</sval>
				<sval type="array" size="2">
					<sval type="int" val="112" />
					<sval type="int" val="121" />
				</sval>
				<sval type="array" size="16">
					<sval type="int" val="150" />
					<sval type="int" val="2" />
					<sval type="int" val="4" />
					<sval type="int" val="8396" />
					<sval type="int" val="4" />
					<sval type="int" val="101" />
					<sval type="int" val="5" />
					<sval type="string" val="A boarding operation is already in progress on this ship" />
					<sval type="int" val="0" />
					<sval type="int" val="0" />
					<sval type="int" val="0" />
					<sval type="int" val="0" />
					<sval type="int" val="0" />
					<sval type="int" val="0" />
					<sval type="int" val="0" />
					<sval type="int" val="0" />
				</sval>
				<sval type="array" size="9">
					<sval type="int" val="1861" />
					<sval type="int" val="131074" />
					<sval type="int" val="2" />
					<sval type="int" val="4" />
					<sval type="int" val="66" />
					<sval type="int" val="4" />
					<sval type="int" val="5000" />
					<sval type="int" val="4" />
					<sval type="int" val="1000" />
				</sval>
				<sval type="array" size="3">
					<sval type="int" val="103" />
					<sval type="int" val="0" />
					<sval type="int" val="0" />
				</sval>
			</sval>
			<sval type="array" size="1">
				<sval type="array" size="2">
					<sval type="int" val="21" />
					<sval type="string" val="" />
				</sval>
			</sval>
			<sval type="array" size="39">
				<sval type="array" size="2">
					<sval type="int" val="6" />
					<sval type="int" val="4" />
				</sval>
				<sval type="array" size="2">
					<sval type="int" val="6" />
					<sval type="int" val="2" />
				</sval>
				<sval type="array" size="2">
					<sval type="int" val="10" />
					<sval type="int" val="4" />
				</sval>
				<sval type="array" size="2">
					<sval type="int" val="10" />
					<sval type="int" val="2" />
				</sval>
				<sval type="array" size="2">
					<sval type="int" val="15" />
					<sval type="int" val="4" />
				</sval>
				<sval type="array" size="2">
					<sval type="int" val="15" />
					<sval type="int" val="2" />
				</sval>
				<sval type="array" size="2">
					<sval type="int" val="17" />
					<sval type="int" val="2" />
				</sval>
				<sval type="array" size="2">
					<sval type="int" val="24" />
					<sval type="int" val="2" />
				</sval>
				<sval type="array" size="2">
					<sval type="int" val="27" />
					<sval type="int" val="5" />
				</sval>
				<sval type="array" size="2">
					<sval type="int" val="28" />
					<sval type="int" val="4" />
				</sval>
				<sval type="array" size="2">
					<sval type="int" val="29" />
					<sval type="int" val="2" />
				</sval>
				<sval type="array" size="2">
					<sval type="int" val="41" />
					<sval type="int" val="2" />
				</sval>
				<sval type="array" size="2">
					<sval type="int" val="42" />
					<sval type="int" val="2" />
				</sval>
				<sval type="array" size="3">
					<sval type="int" val="42" />
					<sval type="int" val="1" />
					<sval type="string" val="---------------------------------------------------------------------------------------------------------------------------------" />
				</sval>
				<sval type="array" size="2">
					<sval type="int" val="42" />
					<sval type="int" val="2" />
				</sval>
				<sval type="array" size="2">
					<sval type="int" val="49" />
					<sval type="int" val="4" />
				</sval>
				<sval type="array" size="2">
					<sval type="int" val="52" />
					<sval type="int" val="5" />
				</sval>
				<sval type="array" size="2">
					<sval type="int" val="53" />
					<sval type="int" val="4" />
				</sval>
				<sval type="array" size="2">
					<sval type="int" val="57" />
					<sval type="int" val="4" />
				</sval>
				<sval type="array" size="2">
					<sval type="int" val="57" />
					<sval type="int" val="2" />
				</sval>
				<sval type="array" size="2">
					<sval type="int" val="82" />
					<sval type="int" val="4" />
				</sval>
				<sval type="array" size="2">
					<sval type="int" val="88" />
					<sval type="int" val="5" />
				</sval>
				<sval type="array" size="2">
					<sval type="int" val="97" />
					<sval type="int" val="4" />
				</sval>
				<sval type="array" size="2">
					<sval type="int" val="103" />
					<sval type="int" val="4" />
				</sval>
				<sval type="array" size="2">
					<sval type="int" val="104" />
					<sval type="int" val="4" />
				</sval>
				<sval type="array" size="2">
					<sval type="int" val="104" />
					<sval type="int" val="4" />
				</sval>
				<sval type="array" size="2">
					<sval type="int" val="105" />
					<sval type="int" val="5" />
				</sval>
				<sval type="array" size="2">
					<sval type="int" val="108" />
					<sval type="int" val="4" />
				</sval>
				<sval type="array" size="2">
					<sval type="int" val="109" />
					<sval type="int" val="5" />
				</sval>
				<sval type="array" size="2">
					<sval type="int" val="112" />
					<sval type="int" val="4" />
				</sval>
				<sval type="array" size="2">
					<sval type="int" val="113" />
					<sval type="int" val="5" />
				</sval>
				<sval type="array" size="2">
					<sval type="int" val="115" />
					<sval type="int" val="4" />
				</sval>
				<sval type="array" size="2">
					<sval type="int" val="116" />
					<sval type="int" val="5" />
				</sval>
				<sval type="array" size="2">
					<sval type="int" val="118" />
					<sval type="int" val="4" />
				</sval>
				<sval type="array" size="2">
					<sval type="int" val="119" />
					<sval type="int" val="5" />
				</sval>
				<sval type="array" size="2">
					<sval type="int" val="121" />
					<sval type="int" val="4" />
				</sval>
				<sval type="array" size="2">
					<sval type="int" val="121" />
					<sval type="int" val="4" />
				</sval>
				<sval type="array" size="2">
					<sval type="int" val="121" />
					<sval type="int" val="2" />
				</sval>
				<sval type="array" size="2">
					<sval type="int" val="121" />
					<sval type="int" val="2" />
				</sval>
			</sval>
			<sval type="int" val="0" />
		</sval>
	</codearray>
</script>
